[
    {
        "title": "Smartphone X",
        "slug": "smartphone-x",
        "description": "A powerful and stylish smartphone with the latest features.",
        "brand": "Brand A",
        "price": 9990000,
        "category": "Smartphones",
        "quantity": 100,
        "sold": 50,
        "images": [],
        "color": "Black",
        "ratings": [],
        "totalRatings": 0,
        "createdAt": "2024-09-27T01:20:30.134715"
    },
    {
        "title": "Gaming Laptop Y",
        "slug": "gaming-laptop-y",
        "description": "A high-performance gaming laptop with powerful graphics.",
        "brand": "Brand B",
        "price": 19990000,
        "category": "Laptops",
        "quantity": 50,
        "sold": 20,
        "images": [],
        "color": "Silver",
        "ratings": [],
        "totalRatings": 0,
        "createdAt": "2024-09-27T01:19:30.134715"
    },
    {
        "title": "Wireless Headphones Z",
        "slug": "wireless-headphones-z",
        "description": "Noise-cancelling wireless headphones with long battery life.",
        "brand": "Brand C",
        "price": 2990000,
        "category": "Headphones",
        "quantity": 75,
        "sold": 30,
        "images": [],
        "color": "White",
        "ratings": [],
        "totalRatings": 0,
        "createdAt": "2024-09-24T01:20:30.134715"
    },
    {
        "title": "Smartwatch Z",
        "slug": "smartwatch-z",
        "description": "A modern smartwatch with fitness tracking and notifications.",
        "brand": "Brand D",
        "price": 4990000,
        "category": "Smartwatches",
        "quantity": 35,
        "sold": 24,
        "images": [],
        "color": "Green",
        "ratings": [],
        "totalRatings": 0,
        "createdAt": "2024-08-21T01:20:30.134715"
    }
]
